odoo/addons/l10n_et_payroll_category/README.rst
odoo/addons/l10n_et_payroll_category/__manifest__.py
odoo/addons/l10n_et_payroll_category/data/hr_salary_rule_category.xml
odoo/addons/l10n_et_payroll_category/readme/CREDITS.rst
odoo/addons/l10n_et_payroll_category/readme/DESCRIPTION.rst
odoo/addons/l10n_et_payroll_category/static/description/icon.png
odoo/addons/l10n_et_payroll_category/static/description/index.html
odoo/addons/l10n_et_payroll_category/static/src/img/main_screenshot.png
odoo14_addon_l10n_et_payroll_category-14.0.1.0.1.dev2.dist-info/METADATA
odoo14_addon_l10n_et_payroll_category-14.0.1.0.1.dev2.dist-info/WHEEL
odoo14_addon_l10n_et_payroll_category-14.0.1.0.1.dev2.dist-info/top_level.txt
odoo14_addon_l10n_et_payroll_category-14.0.1.0.1.dev2.dist-info/RECORD
